doonroom_db/__init__.py
doonroom_db/database.py
doonroom_db/download.py
doonroom_db/main.py
doonroom_db/parser.py
doonroom_db/py.typed
doonroom_db-0.1.0.dist-info/LICENSE.txt
doonroom_db-0.1.0.dist-info/METADATA
doonroom_db-0.1.0.dist-info/WHEEL
doonroom_db-0.1.0.dist-info/entry_points.txt
doonroom_db-0.1.0.dist-info/top_level.txt
doonroom_db-0.1.0.dist-info/RECORD
