Metadata-Version: 2.1
Name: doonroom-db
Version: 0.1.0
Summary: 同人音声の部屋 (http://doonroom.blog.jp/) Unofficial DB
Home-page: https://github.com/eggplants/doonroom_db
Author: eggplants
Author-email: w10776e8w@yahoo.co.jp
License: MIT
Platform: UNKNOWN
Classifier: License :: OSI Approved :: MIT License
Classifier: Programming Language :: Python
Classifier: Programming Language :: Python :: 3
Classifier: Programming Language :: Python :: 3 :: Only
Classifier: Programming Language :: Python :: 3.7
Classifier: Programming Language :: Python :: 3.8
Classifier: Programming Language :: Python :: 3.9
Classifier: Programming Language :: Python :: 3.10
Classifier: Programming Language :: Python :: Implementation :: CPython
Requires-Python: >=3.7
License-File: LICENSE.txt
Requires-Dist: beautifulsoup4 (>=4.11.1)
Requires-Dist: lxml (>=4.8.0)
Requires-Dist: types-beautifulsoup4
Provides-Extra: dev
Requires-Dist: black ; extra == 'dev'
Requires-Dist: flake8 ; extra == 'dev'
Requires-Dist: mypy ; extra == 'dev'
Requires-Dist: pytest ; extra == 'dev'
Requires-Dist: setuptools (>=46.4.0) ; extra == 'dev'
Requires-Dist: types-setuptools ; extra == 'dev'
